li_aws_helper/__init__.py
li_aws_helper/aws_config.py
li_aws_helper/exceptions.py
li_aws_helper/main.py
li_aws_helper/sts_client.py
li_aws_helper-0.3.0.dist-info/LICENSE
li_aws_helper-0.3.0.dist-info/METADATA
li_aws_helper-0.3.0.dist-info/WHEEL
li_aws_helper-0.3.0.dist-info/entry_points.txt
li_aws_helper-0.3.0.dist-info/RECORD
