Metadata-Version: 2.1
Name: li-aws-helper
Version: 0.3.0
Summary: Package that helps manage aws credentials
Author: Alini Ribeiro
Author-email: aliniribeiroo@gmail.com
Requires-Python: >=3.9,<4.0
Classifier: Programming Language :: Python :: 3
Classifier: Programming Language :: Python :: 3.9
Classifier: Programming Language :: Python :: 3.10
Classifier: Programming Language :: Python :: 3.11
Classifier: Programming Language :: Python :: 3.12
Requires-Dist: boto3 (>=1.24.71,<2.0.0)
Requires-Dist: requests-mock (>=1.10.0,<2.0.0)
Requires-Dist: typer (>=0.6.1,<0.7.0)
